MANIFEST.in
README.md
README.rst
setup.cfg
setup.py
fairml/__init__.py
fairml/black_box_functionality.py
fairml/graphing.py
fairml/non_linear_expansion.py
fairml/orthogonal_projection.py
fairml/perturbation_strategies.py
fairml/utils.py
fairml.egg-info/PKG-INFO
fairml.egg-info/SOURCES.txt
fairml.egg-info/dependency_links.txt
fairml.egg-info/not-zip-safe
fairml.egg-info/requires.txt
fairml.egg-info/top_level.txt