Metadata-Version: 1.1
Name: fairml
Version: 0.1.1.5rc3
Summary: Module for measuring feature dependence for black-box models
Home-page: https://github.com/adebayoj/fairml
Author: Julius Adebayo
Author-email: julius.adebayo@gmail.com
License: MIT
Platform: UNKNOWN
Classifier: Intended Audience :: Science/Research
Classifier: License :: OSI Approved :: MIT License
Classifier: Natural Language :: English
Classifier: Operating System :: OS Independent
Classifier: Programming Language :: Python
Classifier: Intended Audience :: Developers
Classifier: Topic :: Scientific/Engineering :: Information Analysis
Classifier: Topic :: Software Development :: Libraries :: Python Modules
